Workbook
Name Categorías: #REF!
Name DESOBJ: Etapa1Analisis[Descripción de objetivo]
Name ID: Etapa1Analisis[ID]
Name META: Etapa1Analisis[Meta]
Name SegmentaciónDeDatos_Categoría: #N/A
Name UNIDADMEDICION: Etapa1Analisis[Medición]

Sheet Portada e índice
A1: PORTADA E ÍNDICE
A15: Contextualización:
A16: La empresa TecnoStudio necesita involucrar sus estrategias dentro de los objetivos de la
A17: empresa. En consecuencia, requiere definir un cuadro de mando integral (Balanced
A18: Scorecard). Para ello, considerar los siguientes datos proporcionados para el modelo de
A19: gestión:
A25: Introducción
A26: Etapa 1. Análisis y Diseño
A27: Etapa 2. Mapa Estratégico
A28: Etapa 3. Objetivos Relevantes
A29: Etapa 4. Tablero de Control
A30: Etapa 5. Dashboard

Sheet Introducción
A1: INTRODUCCIÓN GENERAL
A2: Instrucciones: Redactar una introducción de mínimo 150 palabras referente a la información que presentarás. Puedes agregar conceptos, expectativas del trabajo o una opinión personal previa a la realización del trabajo.
B6: Las metricas o indicadores que se utilizan se dividen en distintas areas las cuales principalmente son precios y costos y estos nos ayudan a enfocarnos en el producto, tambien nos acompaña el desempeño financiero que nos mide el retorno de cada proyecto, tambien la calendarizacion que son las mas comunes para los proyectos de ejecucion, adicional los recursos que son llos as metricas similares a los gastos y los gastos son enfocados a investigar el porcentaje de los presupuestos. Los KPI se enfocan en principalmente 4 situaciones, que son mostrar tendencias, señalar el pasado, señalar el presente, y resaltar las areas de oportunidad que puedan existir, ademas esto ayuda a las organizaciones por que definen el camino que hay que tomar para mejorar, asi como cuando hay que tomar para mejorar.

Sheet Etapa 1. Análisis Ext. e Int.
A1: Etapa 1. Análisis Externo e Interno
A2: Indicaciones para esta hoja
A3: 1 | B3: Rellene la columa de "Descripción de objetivos" eligiendo las opciones conforme al video.
A4: 2 | B4: Establezca en la columna de "Meta" el valor porcentual sugerido en el video. Este valor es un valor sugerido, puede ser cambiado para efectos de la entrega.
A5: 3 | B5: Fije en la columna de "Unidad de Medición", la frecuencia con que se reporta el objetivo.
C6: Los datos de esta columna son propuestos por el alumno
A7: ID | B7: Descripción de objetivo | C7: Meta | D7: Medición
A8: 1 | B8: Incrementar % de rentabilidad | C8: 0.5 | D8: Anual
A9: 2 | B9: Aumentar ingreso de ventas | C9: 0.2 | D9: Anual
A10: 3 | B10: Fidelización de los clientes | C10: 0.85 | D10: Anual
A11: 4 | B11: Incrementar eficiencia del proceso | C11: 0.92 | D11: Mensual
A12: 5 | B12: Control de calidad para reducción de defectos | C12: 0.01 | D12: Mensual
A13: 6 | B13: Reducir tiempo de ciclo | C13: 20 | D13: Anual
A14: 7 | B14: Capacitación total del personal | C14: 1 | D14: Anual
A15: 8 | B15: índice de rotación menor | C15: 0.02 | D15: Mensual
A16: 9 | B16: Incrementar inversión en herramientas para los departamentos e inversión en investigación | C16: 0.2 | D16: Anual
B18: Listado de Objetivos (No modificar) | C18: Indicador | D18: Nota del mentor: La etapa de análisis interno y externo es un proceso que se utiliza para definir objetivos en una organización. Esta etapa implica la recopilación de información sobre el entorno externo y los recursos internos de la organización para identificar sus fortalezas, debilidades, oportunidades y amenazas. El análisis interno se enfoca en los recursos, habilidades, capacidades y limitaciones de la organización, incluyendo su estructura, cultura, procesos, sistemas y equipos. Este análisis puede ayudar a la organización a identificar sus ventajas competitivas, áreas de mejora y oportunidades para optimizar su desempeño. Por otro lado, el análisis externo se enfoca en el entorno en el que la organización opera, incluyendo el mercado, la competencia, los clientes, proveedores, regulaciones, tendencias económicas y tecnológicas, entre otros. Este análisis puede ayudar a la organización a identificar oportunidades y amenazas externas que pueden impactar su desempeño y a desarrollar estrategias para aprovechar o mitigar estos factores.
B19: Incrementar % de rentabilidad | C19: (Utilidad neta) / (Ingresos totales) * 100%
B20: Aumentar ingreso de ventas | C20: (Ventas actuales-Ventas anterior) / (ventas periodo anterior)*100%
B21: Fidelización de los clientes | C21: (No. Clientes con valoración mayor a neutro o satisfactorio) / (total clientes encuestados) * 100%
B22: Incrementar eficiencia del proceso | C22: (Unidades producidas) / (Costo producción) * 100%
B23: Control de calidad para reducción de defectos | C23: (No. Fallas) / (Total de servicios) * 100%
B24: Reducir tiempo de ciclo | C24: Sumatoria de operaciones (minutos)
B25: Capacitación total del personal | C25: (No. Capacitaciones ejecutadas) / (No. Capacitaciones planificadas) * 100%
B26: índice de rotación menor | C26: Rotación neta / Número empleados * 100%
B27: Incrementar inversión en herramientas para los departamentos e inversión en investigación | C27: Valor de la inversión (Millones o miles)

Sheet Etapa 2. Mapa estratégico
A1: Etapa 2. Mapa Estratégico
A2: Indicaciones para esta hoja
A3: 1 | B3: Establece los objetivos estratégicos acorde con la visión de la empresa.
A5: Visión Estratégica | B5: Financiera | C5: Incrementar % de rentabilidad | D5: Aumentar ingreso de ventas | E5: Reducir tiempo de ciclo
B6: Clientes | C6: Fidelización de los clientes | D6: Reducir tiempo de ciclo | E6: Aumentar ingreso de ventas
B7: Procesos | C7: Incrementar eficiencia del proceso | D7: Reducir tiempo de ciclo | E7: Control de calidad para reducción de defectos
B8: Aprendizaje y Desarrollo | C8: Capacitación total del personal | D8: Incrementar inversión en herramientas para los departamentos e inversión en investigación | E8: índice de rotación menor
D12: Nota del mentor: La etapa de diseño de un mapa estratégico es un proceso clave en la elaboración de un cuadro de mando integral (CMI). Un mapa estratégico es una herramienta visual que muestra la relación entre los objetivos estratégicos de una organización y los factores críticos de éxito que deben alcanzarse para lograr esos objetivos. En esta etapa, se identifican los objetivos estratégicos de la organización y se organizan en perspectivas que reflejan los diferentes aspectos del desempeño empresarial. Por lo general, estas perspectivas incluyen Financiera, Clientes, Procesos internos y Aprendizaje y Crecimiento. Una vez identificados los objetivos y perspectivas, se establecen relaciones de causa y efecto entre ellos para construir el mapa estratégico. Es decir, se identifican las causas y consecuencias de cada objetivo estratégico, y se establecen relaciones lógicas entre ellos. El mapa estratégico muestra cómo la consecución de objetivos en una perspectiva afecta la consecución de objetivos en otras perspectivas.

Sheet Etapa 3. Objetivos Relevantes
A1: Etapa 3. Objetivos e indicadores claves
A2: Indicaciones para esta hoja
A3: 1 | B3: Elija en la columna "Categoría" las opciones acorde con la dimensión estratégica.
A4: 2 | B4: Elija en la columna "Objetivo-Descripción" el objetivo estratégico
A5: 3 | B5: Verifique que el indicador es correcto y corresponde con el objetivo propuesto
A6: 4 | B6: Elija la opción adecuada en la columna "Unidad de medida".
A7: 5 | B7: Rellene la columna "Avance Actual" con valores sugeridos suyos o propuestos por el video.
F8: Los datos de esta columna son propuestos por el alumno
A9: ID | B9: Categoría | C9: Objetivo-Descripción | D9: Indicador | E9: Unidad de medida
A10: 1 | B10: Financiera | C10: Incrementar % de rentabilidad | D10: =VLOOKUP(Tabla5[[#This Row],[Objetivo-Descripción]],Listadeobjetivos[],2,FALSE) -> (Utilidad neta) / (Ingresos totales) * 100% | E10: Porcentaje | F10: 0.1256
A11: 2 | B11: Financiera | C11: Aumentar ingreso de ventas | D11: =VLOOKUP(Tabla5[[#This Row],[Objetivo-Descripción]],Listadeobjetivos[],2,FALSE) -> (Ventas actuales-Ventas anterior) / (ventas periodo anterior)*100% | E11: Porcentaje | F11: 0.1428
A12: 3 | B12: Clientes | C12: Fidelización de los clientes | D12: =VLOOKUP(Tabla5[[#This Row],[Objetivo-Descripción]],Listadeobjetivos[],2,FALSE) -> (No. Clientes con valoración mayor a neutro o satisfactorio) / (total clientes encuestados) * 100% | E12: Porcentaje | F12: 0.3
A13: 4 | B13: Procesos | C13: Incrementar eficiencia del proceso | D13: =VLOOKUP(Tabla5[[#This Row],[Objetivo-Descripción]],Listadeobjetivos[],2,FALSE) -> (Unidades producidas) / (Costo producción) * 100% | E13: Porcentaje | F13: 0.4
A14: 5 | B14: Procesos | C14: Control de calidad para reducción de defectos | D14: =VLOOKUP(Tabla5[[#This Row],[Objetivo-Descripción]],Listadeobjetivos[],2,FALSE) -> (No. Fallas) / (Total de servicios) * 100% | E14: Porcentaje | F14: 0.01
A15: 6 | B15: Procesos | C15: Reducir tiempo de ciclo | D15: =VLOOKUP(Tabla5[[#This Row],[Objetivo-Descripción]],Listadeobjetivos[],2,FALSE) -> Sumatoria de operaciones (minutos) | E15: Horas | F15: 135
A16: 7 | B16: Aprendizaje y Desarrollo | C16: Capacitación total del personal | D16: =VLOOKUP(Tabla5[[#This Row],[Objetivo-Descripción]],Listadeobjetivos[],2,FALSE) -> (No. Capacitaciones ejecutadas) / (No. Capacitaciones planificadas) * 100% | E16: Porcentaje | F16: 2.25
A17: 8 | B17: Aprendizaje y Desarrollo | C17: índice de rotación menor | D17: =VLOOKUP(Tabla5[[#This Row],[Objetivo-Descripción]],Listadeobjetivos[],2,FALSE) -> Rotación neta / Número empleados * 100% | E17: Porcentaje | F17: 0.1826
A18: 9 | B18: Aprendizaje y Desarrollo | C18: Incrementar inversión en herramientas para los departamentos e inversión en investigación | D18: =VLOOKUP(Tabla5[[#This Row],[Objetivo-Descripción]],Listadeobjetivos[],2,FALSE) -> Valor de la inversión (Millones o miles) | E18: Millones | F18: 7000000

Sheet Etapa 4. Tablero de control
A1: Etapa 4. Tablero de control
A2: Indicaciones para esta hoja
A3: 1 | B3: Verifica que las columnas muestren correctamente los datos establecidos en hojas anteriores, si es necesario ajusta el formato de las celdas.
A4: 2 | B4: Establezca los parámetros de Óptimo, Suficiente y Deficiente acorde con su criterio o el video propuesto.
A5: 3 | B5: Elija el encargado o responsable de dar seguimiento al objetivo clave.
A7: Categoría | B7: Objetivo | C7: Unidad de Medida | D7: Avance Actual | E7: Meta propuesta | F7: Medición | G7: Óptimo | H7: Suficiente | I7: Deficiente | J7: Responsable / Encargado
A8: ='Etapa 3. Objetivos Relevantes'!B10 -> Financiera | B8: ='Etapa 3. Objetivos Relevantes'!C10 -> Incrementar % de rentabilidad | C8: ='Etapa 3. Objetivos Relevantes'!E10 -> Porcentaje | D8: ='Etapa 3. Objetivos Relevantes'!F10 -> 0.1256 | E8: ='Etapa 1. Análisis Ext. e Int.'!C8 -> 0.5 | F8: ='Etapa 1. Análisis Ext. e Int.'!D8 -> Anual | G8: 0.5 | H8: 0.2 | I8: 0.05 | J8: Gerente
A9: ='Etapa 3. Objetivos Relevantes'!B11 -> Financiera | B9: ='Etapa 3. Objetivos Relevantes'!C11 -> Aumentar ingreso de ventas | C9: ='Etapa 3. Objetivos Relevantes'!E11 -> Porcentaje | D9: ='Etapa 3. Objetivos Relevantes'!F11 -> 0.1428 | E9: ='Etapa 1. Análisis Ext. e Int.'!C9 -> 0.2 | F9: ='Etapa 1. Análisis Ext. e Int.'!D9 -> Anual | G9: 0.2 | H9: 0.1 | I9: 0.05 | J9: Comercial
A10: ='Etapa 3. Objetivos Relevantes'!B12 -> Clientes | B10: ='Etapa 3. Objetivos Relevantes'!C12 -> Fidelización de los clientes | C10: ='Etapa 3. Objetivos Relevantes'!E12 -> Porcentaje | D10: ='Etapa 3. Objetivos Relevantes'!F12 -> 0.3 | E10: ='Etapa 1. Análisis Ext. e Int.'!C10 -> 0.85 | F10: ='Etapa 1. Análisis Ext. e Int.'!D10 -> Anual | G10: 0.95 | H10: 0.9 | I10: 0.8 | J10: Operaciones
A11: ='Etapa 3. Objetivos Relevantes'!B13 -> Procesos | B11: ='Etapa 3. Objetivos Relevantes'!C13 -> Incrementar eficiencia del proceso | C11: ='Etapa 3. Objetivos Relevantes'!E13 -> Porcentaje | D11: ='Etapa 3. Objetivos Relevantes'!F13 -> 0.4 | E11: ='Etapa 1. Análisis Ext. e Int.'!C11 -> 0.92 | F11: ='Etapa 1. Análisis Ext. e Int.'!D11 -> Mensual | G11: 0.9 | H11: 0.8 | I11: 0.7 | J11: Operaciones
A12: ='Etapa 3. Objetivos Relevantes'!B14 -> Procesos | B12: ='Etapa 3. Objetivos Relevantes'!C14 -> Control de calidad para reducción de defectos | C12: ='Etapa 3. Objetivos Relevantes'!E14 -> Porcentaje | D12: ='Etapa 3. Objetivos Relevantes'!F14 -> 0.01 | E12: ='Etapa 1. Análisis Ext. e Int.'!C12 -> 0.01 | F12: ='Etapa 1. Análisis Ext. e Int.'!D12 -> Mensual | G12: 0.02 | H12: 0.06 | I12: 0.1 | J12: Operaciones
A13: ='Etapa 3. Objetivos Relevantes'!B15 -> Procesos | B13: ='Etapa 3. Objetivos Relevantes'!C15 -> Reducir tiempo de ciclo | C13: ='Etapa 3. Objetivos Relevantes'!E15 -> Horas | D13: ='Etapa 3. Objetivos Relevantes'!F15 -> 135 | E13: ='Etapa 1. Análisis Ext. e Int.'!C13 -> 20 | F13: ='Etapa 1. Análisis Ext. e Int.'!D13 -> Anual | G13: 10 | H13: 20 | I13: 30 | J13: Operaciones
A14: ='Etapa 3. Objetivos Relevantes'!B16 -> Aprendizaje y Desarrollo | B14: ='Etapa 3. Objetivos Relevantes'!C16 -> Capacitación total del personal | C14: ='Etapa 3. Objetivos Relevantes'!E16 -> Porcentaje | D14: ='Etapa 3. Objetivos Relevantes'!F16 -> 2.25 | E14: ='Etapa 1. Análisis Ext. e Int.'!C14 -> 1 | F14: ='Etapa 1. Análisis Ext. e Int.'!D14 -> Anual | G14: 0.9 | H14: 0.8 | I14: 0.7 | J14: RH
A15: ='Etapa 3. Objetivos Relevantes'!B17 -> Aprendizaje y Desarrollo | B15: ='Etapa 3. Objetivos Relevantes'!C17 -> índice de rotación menor | C15: ='Etapa 3. Objetivos Relevantes'!E17 -> Porcentaje | D15: ='Etapa 3. Objetivos Relevantes'!F17 -> 0.1826 | E15: ='Etapa 1. Análisis Ext. e Int.'!C15 -> 0.02 | F15: ='Etapa 1. Análisis Ext. e Int.'!D15 -> Mensual | G15: 0.05 | H15: 0.06 | I15: 0.08 | J15: RH
A16: ='Etapa 3. Objetivos Relevantes'!B18 -> Aprendizaje y Desarrollo | B16: ='Etapa 3. Objetivos Relevantes'!C18 -> Incrementar inversión en herramientas para los departamentos e inversión en investigación | C16: ='Etapa 3. Objetivos Relevantes'!E18 -> Millones | D16: ='Etapa 3. Objetivos Relevantes'!F18 -> 7000000 | E16: ='Etapa 1. Análisis Ext. e Int.'!C16 -> 0.2 | F16: ='Etapa 1. Análisis Ext. e Int.'!D16 -> Anual | G16: 10 | H16: 5 | I16: 2 | J16: RH

Sheet Etapa 5. Dashboard
A1: Etapa 5. Resultados
A2: Indicaciones para esta hoja
A3: 1 | B3: Elabora un gráfico por cada objetivo de cada perspectiva de la visión estratégica que contraste la meta propuesta contra el avance actual.
A4: 2 | B4: Los gráficos deberán tener título, ejes titulados, leyendas y unidades. Se sugiere cambies el diseño, estilo y paleta de colores.
A5: 3 | B5: Adicionalmente puedes dar formato a los diferentes gráficos.
A7: PERSPECTIVA FINANCIERA
A25: CLIENTES
A44: PROCESOS
A62: APRENDIZAJE Y DESARROLLO

Sheet Conclusión
A1: CONCLUSIÓN (150 PALABRAS)
A3: En los proyectos digitales es el proceso de gestion de cambios criticos, y por lo tanto es muy importante tener de forma basica e importante un balance entre los recursos ecomonicos y humanos. Y es por eso que en este sentido el proceso de gestion de cambio debe ser controlado por un equipo de profesionales que represente todas las areas del proyecto para que nos ayuden a evaluar, priorizar, planear, aprobar e implementar. Esta actividad me parecio muy importante por que asi nos orientamos nosotros como desarrolladores a saber como funcionan todos aquellos cambios que pueden implementarse en la creacion de un proyecto al igual como calcualr el tiempo por cada actividad y programa a desarrollar, el saber exactamente con las formulas todo aquello que se calcula. Tomando en cuenta que para que un proyecto pueda ser rentable se necesita evaluar el costo total de la vida del proyecto y de esta manera es posible determinar la ganancia deseada en cada momento del ciclo lo cual nos ayuda a alcanzar una rentabilidad propia.
